setup.py
shinkenplugins/__init__.py
shinkenplugins.plugins.x224.egg-info/PKG-INFO
shinkenplugins.plugins.x224.egg-info/SOURCES.txt
shinkenplugins.plugins.x224.egg-info/dependency_links.txt
shinkenplugins.plugins.x224.egg-info/entry_points.txt
shinkenplugins.plugins.x224.egg-info/namespace_packages.txt
shinkenplugins.plugins.x224.egg-info/requires.txt
shinkenplugins.plugins.x224.egg-info/top_level.txt
shinkenplugins/plugins/__init__.py
shinkenplugins/plugins/x224/__init__.py
shinkenplugins/plugins/x224/x224.py